poorlib/__init__.py
poorlib/crypto/__init__.py
poorlib/crypto/aes_chiper.py
poorlib/filecreator/__init__.py
poorlib/filecreator/csv_excel_file_creator.py
poorlib/utils/__init__.py
poorlib/utils/code_receipt_utils.py
poorlib/utils/list_utils.py
poorlib-0.0.8.dist-info/METADATA
poorlib-0.0.8.dist-info/WHEEL
poorlib-0.0.8.dist-info/top_level.txt
poorlib-0.0.8.dist-info/RECORD
