Metadata-Version: 2.1
Name: poorlib
Version: 0.0.8
Summary: Python library for poor-man
Author: Farhan Purdi
